src/__init__.py
src/models/__init__.py
src/models/enums.py
src/models/models.py
src/models/schemas.py
ec_data_models-0.2.0.dist-info/METADATA
ec_data_models-0.2.0.dist-info/WHEEL
ec_data_models-0.2.0.dist-info/RECORD
