Metadata-Version: 2.4
Name: ec-data-models
Version: 0.2.0
Summary: Repository for SQLAlchemy models with Alembic migrations
Project-URL: Homepage, https://www.entrepreneur-club.org/
Project-URL: Repository, https://github.com/eth-entrepreneur-club/Data-Models
Author-email: it@entrepreneur-club.org
License-Expression: MIT
Classifier: Programming Language :: Python :: 3
Classifier: Programming Language :: Python :: 3.12
Requires-Python: <4.0,>=3.12
Requires-Dist: sqlmodel<0.1.0,>=0.0.16
Provides-Extra: dev
Requires-Dist: alembic-postgresql-enum>=1.8.0; extra == 'dev'
Requires-Dist: alembic<2.0,>=1.10; extra == 'dev'
Requires-Dist: build<2.0,>=1.0; extra == 'dev'
Requires-Dist: dotenv>=0.9.9; extra == 'dev'
Requires-Dist: mypy<2.0,>=1.1; extra == 'dev'
Requires-Dist: pre-commit<4.0,>=3.0; extra == 'dev'
Requires-Dist: pytest-cov<5.0,>=4.1; extra == 'dev'
Requires-Dist: pytest<8.0,>=7.2; extra == 'dev'
Requires-Dist: ruff<1.0,>=0.5; extra == 'dev'
Provides-Extra: postgres
Requires-Dist: psycopg[binary]<4.0,>=3.1; extra == 'postgres'
